pythonLogs/.env.example
pythonLogs/__init__.py
pythonLogs/basic_log.py
pythonLogs/constants.py
pythonLogs/factory.py
pythonLogs/log_utils.py
pythonLogs/memory_utils.py
pythonLogs/settings.py
pythonLogs/size_rotating.py
pythonLogs/thread_safety.py
pythonLogs/timed_rotating.py
pythonlogs-5.0.2.dist-info/METADATA
pythonlogs-5.0.2.dist-info/WHEEL
pythonlogs-5.0.2.dist-info/licenses/LICENSE
pythonlogs-5.0.2.dist-info/RECORD
