Metadata-Version: 2.4
Name: pythonLogs
Version: 5.0.2
Summary: High-performance Python logging library with file rotation and optimized caching for better performance
License: MIT
License-File: LICENSE
Keywords: python3,python-3,python,log,logging,logger,logutils,log-utils,pythonLogs
Author: Daniel Costa
Author-email: danieldcsta@gmail.com
Maintainer: Daniel Costa
Requires-Python: >=3.12,<4.0
Classifier: Development Status :: 5 - Production/Stable
Classifier: Environment :: Other Environment
Classifier: Intended Audience :: Developers
Classifier: License :: OSI Approved :: MIT License
Classifier: Natural Language :: English
Classifier: Operating System :: OS Independent
Classifier: Programming Language :: Python :: 3
Classifier: Programming Language :: Python :: 3.12
Classifier: Programming Language :: Python :: 3.13
Classifier: Programming Language :: Python :: 3.14
Classifier: Programming Language :: Python :: 3 :: Only
Classifier: Topic :: Software Development :: Libraries :: Python Modules
Requires-Dist: pydantic-settings (==2.11.0)
Requires-Dist: python-dotenv (>=1.1.1,<2.0.0)
Project-URL: Homepage, https://pypi.org/project/pythonLogs
Project-URL: Repository, https://github.com/ddc/pythonLogs
